imap2dict/__init__.py
imap2dict/mail_client.py
imap2dict-0.1.2.dist-info/LICENSE
imap2dict-0.1.2.dist-info/METADATA
imap2dict-0.1.2.dist-info/WHEEL
imap2dict-0.1.2.dist-info/top_level.txt
imap2dict-0.1.2.dist-info/RECORD
