Metadata-Version: 2.1
Name: imap2dict
Version: 0.1.2
Summary: imap2dict: Receiving and deleting email on an IMAP4 server.
Home-page: https://github.com/sikkimtemi/imap2dict
Download-URL: https://github.com/sikkimtemi/imap2dict
Author: TAKAHASHI Taro
Author-email: takahashi.taro@takedasystem.com
Maintainer: TAKAHASHI Taro
Maintainer-email: takahashi.taro@takedasystem.com
License: MIT
Keywords: imap imap4 json
Classifier: License :: OSI Approved :: MIT License
Classifier: Programming Language :: Python :: 3.6
License-File: LICENSE
Requires-Dist: pytz (>=2020.1)
